dbt_select_builder/__init__.py
dbt_select_builder/helper.py
dbt_select_builder/helper_test.py
dbt_select_builder/operator.py
dbt_select_builder/operator_test.py
dbt_select_builder/resolved.py
dbt_select_builder/unresolved.py
dbt_select_builder-0.1.0.dist-info/licenses/LICENSE
dbt_select_builder-0.1.0.dist-info/METADATA
dbt_select_builder-0.1.0.dist-info/WHEEL
dbt_select_builder-0.1.0.dist-info/top_level.txt
dbt_select_builder-0.1.0.dist-info/RECORD
