Metadata-Version: 2.4
Name: dbt-select-builder
Version: 0.1.0
Summary: Add your description here
Requires-Python: >=3.10
License-File: LICENSE
Dynamic: license-file
